Workbook

Sheet Ledger
A1: Source | B1: Item | C1: Amount (EGP) | D1: Direction | E1: Category | F1: Partner | G1: Status
A2: Camp Batch 1 | B2: Student 1 | C2: 20000 | D2: In | E2: Camp income | G2: Done
A3: Camp Batch 1 | B3: Student 2 | C3: 18000 | D3: In | E3: Camp income | G3: Done
A4: Camp Batch 1 | B4: Student 3 | C4: 6000 | D4: In | E4: Camp income | G4: Done
A5: Camp Batch 1 | B5: Student 4 | C5: 12000 | D5: In | E5: Camp income | G5: Done
A6: Camp Batch 1 | B6: Student 5 | C6: 12000 | D6: In | E6: Camp income | G6: Done
A7: Camp Batch 1 | B7: Student 6 | C7: 10000 | D7: In | E7: Camp income | G7: Done
A8: Camp Batch 1 | B8: Student 7 | C8: 9000 | D8: In | E8: Camp income | G8: Done
A9: Camp Batch 1 | B9: Student 8 | C9: 11000 | D9: In | E9: Camp income | G9: Done
A10: Camp Batch 1 | B10: Student 9 | C10: 5000 | D10: In | E10: Camp income | G10: Done
A11: Camp Batch 1 | B11: Student 10 (installment still to come) | C11: 5000 | D11: In | E11: Camp income | G11: Expected
A12: Camp Batch 1 | B12: Student 11 | C12: 1000 | D12: In | E12: Camp income | G12: Done
A13: Camp Batch 1 | B13: Student 12 | C13: 24000 | D13: In | E13: Camp income | G13: Done
... A46: Design house | B46: Designer cost | C46: 1000 | D46: Out | E46: Designer cost | G46: Done
A47: Partner withdrawals | B47: Withdrawal | C47: 4000 | D47: Out | E47: Partner withdrawal | F47: Sayyed | G47: Done
A48: Partner withdrawals | B48: Withdrawal | C48: 20000 | D48: Out | E48: Partner withdrawal | F48: Retro | G48: Done
A49: Partner withdrawals | B49: Withdrawal | C49: 8000 | D49: Out | E49: Partner withdrawal | F49: Badr | G49: Done
A50: Partner withdrawals | B50: Withdrawal | C50: 30000 | D50: Out | E50: Partner withdrawal | F50: Retro | G50: Done
A51: Partner withdrawals | B51: Withdrawal | C51: 3000 | D51: Out | E51: Partner withdrawal | F51: Sayyed | G51: Done
A52: Partner withdrawals | B52: Withdrawal | C52: 2000 | D52: Out | E52: Partner withdrawal | F52: Badr | G52: Done
A53: Partner withdrawals | B53: Withdrawal | C53: 2500 | D53: Out | E53: Partner withdrawal | F53: Retro | G53: Done

Sheet Assumptions
A3: Holder | B3: Old split: Camp income | C3: Old split: design house income | D3: New split (from close)
A4: Badr | B4: 0.3 | C4: 0.25 | D4: 0.25
A5: Sayyed | B5: 0.2 | C5: 0.25 | D5: 0.25
A6: Retro | B6: 0.15 | C6: 0.15 | D6: 0.25
A7: Mo | B7: 0.15 | C7: 0.15 | D7: 0.25
A8: Capital | B8: 0.2 | C8: 0.2 | D8: 0
A9: Total | B9: =SUM(B4:B8) | C9: =SUM(C4:C8) | D9: =SUM(D4:D8)
A11: Inputs
A12: Fixed costs per month, working figure (EGP) | B12: 11500
A13: Freelance Ready seat price (EGP) | B13: 9000
A14: Cash reserve target (months of fixed costs) | B14: 2
A15: Cash reserve target (EGP) | B15: 23000
A16: Tier 1 partner salary pool per month (EGP) | B16: =B38
A17: Number of partners | B17: 4
A18: Derived
A19: Break-even, current rule (EGP a month) | B19: =B12/B8
A20: full-price seats a month | B20: =B19/B13
A21: Break-even, costs paid first (EGP a month) | B21: =B12
A22: full-price seats a month | B22: =B21/B13
A24: Fixed cost build-up (monthly, EGP)
A25: Salaries | B25: 5000
A26: Editor: low | B26: 4000
A27: Editor: high | B27: 6000
A28: Editor: used (midpoint) | B28: 5000
A29: Software subscriptions | B29: 1000
A30: Ads tools | B30: 500
A31: Fixed costs, low case | B31: =B25+B26+B29+B30
A32: Fixed costs, high case | B32: =B25+B27+B29+B30
A33: Reserve target, low case (EGP) | B33: =B31*B14
A34: Reserve target, high case (EGP) | B34: =B32*B14
A36: Partner salary tiers
A37: Tier | B37: Pool per month (EGP) | C37: Trigger: monthly collected income (EGP)
A38: Tier 1 | B38: 10000 | C38: =ROUND((B12+B38)*1.25/5000,0)*5000
A39: Tier 2 | B39: 20000 | C39: =ROUND((B12+B39)*1.25/5000,0)*5000
A40: Tier 3 | B40: 30000 | C40: =ROUND((B12+B40)*1.25/5000,0)*5000

Sheet Cycle Position
B5: =SUMIFS(Ledger!$C$2:$C$200,Ledger!$E$2:$E$200,"Camp income",Ledger!$G$2:$G$200,"Done") | C5: =SUMIFS(Ledger!$C$2:$C$200,Ledger!$E$2:$E$200,"Camp income")
B6: =SUMIFS(Ledger!$C$2:$C$200,Ledger!$E$2:$E$200,"Design house income",Ledger!$G$2:$G$200,"Done") | C6: =SUMIFS(Ledger!$C$2:$C$200,Ledger!$E$2:$E$200,"Design house income")
B7: =B5+B6 | C7: =C5+C6
B8: =SUMIFS(Ledger!$C$2:$C$200,Ledger!$E$2:$E$200,"Camp cost",Ledger!$G$2:$G$200,"Done") | C8: =SUMIFS(Ledger!$C$2:$C$200,Ledger!$E$2:$E$200,"Camp cost")
B9: =SUMIFS(Ledger!$C$2:$C$200,Ledger!$E$2:$E$200,"Designer cost",Ledger!$G$2:$G$200,"Done") | C9: =SUMIFS(Ledger!$C$2:$C$200,Ledger!$E$2:$E$200,"Designer cost")
B10: =B8+B9 | C10: =C8+C9
B11: =SUMIFS(Ledger!$C$2:$C$200,Ledger!$E$2:$E$200,"Partner withdrawal",Ledger!$G$2:$G$200,"Done") | C11: =SUMIFS(Ledger!$C$2:$C$200,Ledger!$E$2:$E$200,"Partner withdrawal")
A12: Cash in the business | B12: 78900 | C12: 65400
B14: =B6/B7 | C14: =C6/C7
B15: =(B6-B9)/B6 | C15: =(C6-C9)/C6

Sheet Function Owners
A4: Function | B4: Applies to | C4: Weight | D4: Badr | E4: Sayyed | F4: Retro | G4: Mo | H4: Accountable count | I4: Supporting count | J4: Check | K4: Staff and contractors
A5: Function one | B5: Both | C5: 1 | D5: A | K5: Contractors
A6: Function two | B6: Both | C6: 1 | E6: A | F6: S
A7: Function three | B7: Core | C7: 1 | D7: S | F7: A
A8: Function four | B8: Camp | C8: 1 | G8: A | K8: Contractors
A9: Function five | B9: Both | C9: 1 | D9: A | E9: S
A10: Function six | B10: Core | C10: 0.5 | E10: A | G10: S
A11: Function seven | B11: Core | C11: 0.5 | E11: S | F11: A | K11: Contractors
A12: Function eight | B12: Both | C12: 1 | E12: A
A13: Function nine | B13: Both | C13: 1 | F13: A
A14: Function ten | B14: Both | C14: 1 | F14: A | K14: Contractors
A20: Accountable per partner (weighted) | D20: =SUMPRODUCT((D5:D19="A")*$C5:$C19) | E20: =SUMPRODUCT((E5:E19="A")*$C5:$C19) | F20: =SUMPRODUCT((F5:F19="A")*$C5:$C19) | G20: =SUMPRODUCT((G5:G19="A")*$C5:$C19)
A21: Supporting per partner (weighted) | D21: =SUMPRODUCT((D5:D19="S")*$C5:$C19) | E21: =SUMPRODUCT((E5:E19="S")*$C5:$C19) | F21: =SUMPRODUCT((F5:F19="S")*$C5:$C19) | G21: =SUMPRODUCT((G5:G19="S")*$C5:$C19)
A22: Total functions per partner (weighted) | D22: =D20+D21 | E22: =E20+E21 | F22: =F20+F21 | G22: =G20+G21
A24: Lines with no accountable partner | H24: =COUNTIF(H5:H19,0)
A25: Lines with more than one accountable partner | H25: =COUNTIF(H5:H19,">1")

Sheet Salaries
A3: Pool per month, sum of X (EGP) | F3: =Assumptions!B38 | G3: =Assumptions!B39 | H3: =Assumptions!B40
A4: Partner | B4: Accountable load | C4: Multiplier | D4: Weighted load | E4: Share of pool | F4: X: Tier 1 | G4: X: Tier 2 | H4: X: Tier 3
A5: Badr | B5: ='Function Owners'!D20 | C5: 1 | D5: =B5*C5 | E5: =D5/$D$9 | F5: =ROUND(F$3*$E5,-2) | G5: =ROUND(G$3*$E5,-2) | H5: =ROUND(H$3*$E5,-2)
A6: Sayyed | B6: ='Function Owners'!E20 | C6: 1 | D6: =B6*C6 | E6: =D6/$D$9 | F6: =ROUND(F$3*$E6,-2) | G6: =ROUND(G$3*$E6,-2) | H6: =ROUND(H$3*$E6,-2)
A7: Retro | B7: ='Function Owners'!F20 | C7: 1 | D7: =B7*C7 | E7: =D7/$D$9 | F7: =F$3-F5-F6-F8 | G7: =G$3-G5-G6-G8 | H7: =H$3-H5-H6-H8
A8: Mo | B8: ='Function Owners'!G20 | C8: 2 | D8: =B8*C8 | E8: =D8/$D$9 | F8: =ROUND(F$3*$E8,-2) | G8: =ROUND(G$3*$E8,-2) | H8: =ROUND(H$3*$E8,-2)
A9: Total | B9: =SUM(B5:B8) | D9: =SUM(D5:D8) | E9: =SUM(E5:E8) | F9: =SUM(F5:F8) | G9: =SUM(G5:G8) | H9: =SUM(H5:H8)
A10: Check: X salaries equal the pool | F10: =IF(F9=F3,"OK","Check") | G10: =IF(G9=G3,"OK","Check") | H10: =IF(H9=H3,"OK","Check")
A12: Trigger income (EGP a month) | F12: =Assumptions!C38 | G12: =Assumptions!C39 | H12: =Assumptions!C40
A14: Base and KPI pay by tier (EGP a month)
A15: Partner | B15: Base T1 (X/2) | C15: KPI max T1 (2X) | D15: Max total T1 | E15: Base T2 | F15: KPI max T2 | G15: Max total T2 | H15: Base T3 | I15: KPI max T3 | J15: Max total T3
A16: =A5 | B16: =F5/2 | C16: =2*F5 | D16: =F5*2.5 | E16: =G5/2 | F16: =2*G5 | G16: =G5*2.5 | H16: =H5/2 | I16: =2*H5 | J16: =H5*2.5
A17: =A6 | B17: =F6/2 | C17: =2*F6 | D17: =F6*2.5 | E17: =G6/2 | F17: =2*G6 | G17: =G6*2.5 | H17: =H6/2 | I17: =2*H6 | J17: =H6*2.5
A18: =A7 | B18: =F7/2 | C18: =2*F7 | D18: =F7*2.5 | E18: =G7/2 | F18: =2*G7 | G18: =G7*2.5 | H18: =H7/2 | I18: =2*H7 | J18: =H7*2.5
A19: =A8 | B19: =F8/2 | C19: =2*F8 | D19: =F8*2.5 | E19: =G8/2 | F19: =2*G8 | G19: =G8*2.5 | H19: =H8/2 | I19: =2*H8 | J19: =H8*2.5
A20: Total | B20: =SUM(B16:B19) | C20: =SUM(C16:C19) | D20: =SUM(D16:D19) | E20: =SUM(E16:E19) | F20: =SUM(F16:F19) | G20: =SUM(G16:G19) | H20: =SUM(H16:H19) | I20: =SUM(I16:I19) | J20: =SUM(J16:J19)
